mc2s/__init__.py
mc2s/cars_data.py
mc2s/carsdata_app.py
mc2s-0.1.dist-info/LICENSE
mc2s-0.1.dist-info/METADATA
mc2s-0.1.dist-info/WHEEL
mc2s-0.1.dist-info/top_level.txt
mc2s-0.1.dist-info/RECORD
