Metadata-Version: 2.1
Name: mc2s
Version: 0.1
Summary: Package to apply MCR-ALS with or without Chan-vese constraint on CARS images
Home-page: https://gitlab.xlim.fr/datacart/mc2s
Author: D. Boildieu
Author-email: damien.boildieu@xlim.fr
License: UNKNOWN
Platform: UNKNOWN
Classifier: Programming Language :: Python :: 3
Classifier: License :: OSI Approved :: MIT License
Classifier: Operating System :: OS Independent
Classifier: Intended Audience :: End Users/Desktop
Classifier: Intended Audience :: Developers
Requires-Python: >=3.8
License-File: LICENSE
Requires-Dist: carsdata
Requires-Dist: numpy
Requires-Dist: matplotlib
Requires-Dist: pillow
